hiton_ezk/__init__.py
hiton_ezk/data_structures.py
hiton_ezk/ezk.py
hiton_ezk/helper.py
hiton_ezk/hiton.py
hiton_ezk/hiton_local.py
hiton_ezk/test_script.py
hiton_ezk-0.0.7.dist-info/LICENSE
hiton_ezk-0.0.7.dist-info/METADATA
hiton_ezk-0.0.7.dist-info/WHEEL
hiton_ezk-0.0.7.dist-info/top_level.txt
hiton_ezk-0.0.7.dist-info/RECORD
