Metadata-Version: 2.1
Name: hiton-ezk
Version: 0.0.7
Summary: Algorithms for constructing causal networks for simulated data
Home-page: https://github.com/mathewtitus/hiton_ezk
Author: Mathew Titus
Author-email: mat@thepredictionlab.com
License: UNKNOWN
Project-URL: Bug Tracker, https://github.com/mathewtitus/hiton_ezk/issues
Platform: UNKNOWN
Classifier: Programming Language :: Python :: 3
Classifier: License :: OSI Approved :: MIT License
Classifier: Operating System :: OS Independent
Requires-Python: >=3.7
License-File: LICENSE
